c9lab_security/__init__.py
c9lab_security/encryption_utility.py
c9lab_security/middleware.py
c9lab_security-0.3.dist-info/LICENSE
c9lab_security-0.3.dist-info/METADATA
c9lab_security-0.3.dist-info/WHEEL
c9lab_security-0.3.dist-info/top_level.txt
c9lab_security-0.3.dist-info/RECORD
