Metadata-Version: 2.1
Name: c9lab-security
Version: 0.3
Summary: Middleware for encrypting and decrypting requests and responses in Django Rest Framework
Home-page: 
Author: C9lab
Author-email: praveen.dhakad@pinakinfosec.com
Classifier: Programming Language :: Python :: 3
Classifier: Framework :: Django
Classifier: License :: OSI Approved :: MIT License
Classifier: Operating System :: OS Independent
License-File: LICENSE
Requires-Dist: Django >=3.0
Requires-Dist: pycryptodome
